nweb/__init__.py
nweb/web.py
nweb-1.0.2.dist-info/METADATA
nweb-1.0.2.dist-info/WHEEL
nweb-1.0.2.dist-info/entry_points.txt
nweb-1.0.2.dist-info/top_level.txt
nweb-1.0.2.dist-info/RECORD
