Metadata-Version: 2.1
Name: nweb
Version: 1.0.2
Summary: nweb
Home-page: https://bsnx.net/4.0/group/pynwebclient
Author: Bjoern Salgert
Author-email: bjoern.salgert@hs-duesseldorf.de
License: UNKNOWN
Platform: UNKNOWN
Classifier: Programming Language :: Python :: 3
Classifier: License :: OSI Approved :: MIT License
Classifier: Operating System :: OS Independent
Requires-Dist: usersettings (>=1.0.7)
Requires-Dist: nwebclient (>=1.0.263)
